hw2d/__init__.py
hw2d/__main__.py
hw2d/__version__.py
hw2d/model.py
hw2d/run.py
hw2d/run2.py
hw2d/gradients/__init__.py
hw2d/gradients/numba_gradients.py
hw2d/gradients/numpy_gradients.py
hw2d/gradients/phiml_gradients.py
hw2d/initializations/__init__.py
hw2d/initializations/fourier_noise.py
hw2d/initializations/sine.py
hw2d/physical_properties/__init__.py
hw2d/physical_properties/numba_properties.py
hw2d/physical_properties/numpy_properties.py
hw2d/poisson_bracket/__init__.py
hw2d/poisson_bracket/numba_arakawa.py
hw2d/poisson_bracket/numpy_arakawa.py
hw2d/poisson_bracket/phiml_arakawa.py
hw2d/poisson_solvers/__init__.py
hw2d/poisson_solvers/numba_fourier_poisson.py
hw2d/poisson_solvers/numpy_fourier_poisson.py
hw2d/poisson_solvers/phiml_fourier_poisson.py
hw2d/utils/__init__.py
hw2d/utils/downsample.py
hw2d/utils/helpers.py
hw2d/utils/io.py
hw2d/utils/latex_format.py
hw2d/utils/namespaces.py
hw2d/utils/performance_comparison.py
hw2d/utils/run_properties.py
hw2d/utils/plot/__init__.py
hw2d/utils/plot/image.py
hw2d/utils/plot/movie.py
hw2d/utils/plot/timetrace.py
hw2d-1.0.4.dist-info/LICENSE
hw2d-1.0.4.dist-info/METADATA
hw2d-1.0.4.dist-info/WHEEL
hw2d-1.0.4.dist-info/top_level.txt
hw2d-1.0.4.dist-info/RECORD
