Metadata-Version: 2.1
Name: hw2d
Version: 1.0.4
Summary: Reference HW2D Implementation in Python
Author-email: Robin Greif <rccgreif@gmail.com>
License: MIT
Project-URL: Changelog, https://github.com/the-rccg/hw2d/blob/main/CHANGES.md
Project-URL: Homepage, https://github.com/the-rccg/hw2d
Project-URL: Issues, https://github.com/the-rccg/hw2d/issues
Keywords: Plasma Physics,Simulation,Turbulence
Classifier: Development Status :: 5 - Production/Stable
Classifier: Intended Audience :: Developers
Classifier: Topic :: Software Development :: Build Tools
Classifier: License :: OSI Approved :: MIT License
Classifier: Programming Language :: Python :: 3
Classifier: Programming Language :: Python :: 3.7
Classifier: Programming Language :: Python :: 3.8
Classifier: Programming Language :: Python :: 3.9
Classifier: Programming Language :: Python :: 3.10
Classifier: Programming Language :: Python :: 3.11
Classifier: License :: OSI Approved :: MIT License
Classifier: Operating System :: OS Independent
Requires-Python: >=3.7.1
License-File: LICENSE
Requires-Dist: pytest
Requires-Dist: fire
Requires-Dist: h5py
Requires-Dist: matplotlib
Requires-Dist: numpy
Requires-Dist: pandas
Requires-Dist: scipy
Requires-Dist: tqdm
Requires-Dist: perfplot
Provides-Extra: accelerators
Requires-Dist: numba ; extra == 'accelerators'
Requires-Dist: phiml ; extra == 'accelerators'
Provides-Extra: develop
Requires-Dist: coverage ; extra == 'develop'
Requires-Dist: pre-commit ; extra == 'develop'
Requires-Dist: pytest ; extra == 'develop'
Requires-Dist: pytest-cov ; extra == 'develop'
Requires-Dist: pytest-mock ; extra == 'develop'
